ds_tut/__init__.py
ds_tut/_modidx.py
ds_tut/core.py
ds_tut/datasets.py
ds_tut/io.py
ds_tut/setup.py
ds_tut/transformers.py
ds_tut-0.0.10.dist-info/LICENSE
ds_tut-0.0.10.dist-info/METADATA
ds_tut-0.0.10.dist-info/WHEEL
ds_tut-0.0.10.dist-info/entry_points.txt
ds_tut-0.0.10.dist-info/top_level.txt
ds_tut-0.0.10.dist-info/RECORD
