Metadata-Version: 2.1
Name: ds-tut
Version: 0.0.10
Summary: Base infrastructure for data science tutorials
Home-page: https://github.com/ephes/ds_tut
Author: Jochen Wersdörfer
Author-email: jochen@wersdoerfer.de
License: Apache Software License 2.0
Keywords: nbdev jupyter notebook python
Classifier: Development Status :: 4 - Beta
Classifier: Intended Audience :: Developers
Classifier: Natural Language :: English
Classifier: Programming Language :: Python :: 3.9
Classifier: Programming Language :: Python :: 3.10
Classifier: License :: OSI Approved :: Apache Software License
Requires-Python: >=3.9
License-File: LICENSE
Requires-Dist: httpx
Requires-Dist: rich
Requires-Dist: jupyterlab
Provides-Extra: dev
Requires-Dist: nbdev ; extra == 'dev'
Requires-Dist: twine ; extra == 'dev'
